als.cpython-37m-darwin.so
alsmodule_pkg/__init__.py
alsmodule_pkg-0.0.1.dist-info/LICENSE
alsmodule_pkg-0.0.1.dist-info/METADATA
alsmodule_pkg-0.0.1.dist-info/WHEEL
alsmodule_pkg-0.0.1.dist-info/top_level.txt
alsmodule_pkg-0.0.1.dist-info/RECORD
