Metadata-Version: 2.1
Name: alsmodule-pkg
Version: 0.0.1
Summary: A simple module to access ambient light sensors samples on Mac OS X
Home-page: UNKNOWN
Author: Jean-Jacques Puig
Author-email: jjp-pypi@espci.fr
License: UNKNOWN
Platform: UNKNOWN
Classifier: Programming Language :: C
Classifier: Programming Language :: Python :: 3
Classifier: License :: OSI Approved :: GNU General Public License v3 or later (GPLv3+)
Classifier: Operating System :: MacOS :: MacOS X
Requires-Python: >=3.7
